app/__init__.py
app/__main__.py
app/app.py
spotify_downloader-0.4.2.dist-info/DESCRIPTION.rst
spotify_downloader-0.4.2.dist-info/METADATA
spotify_downloader-0.4.2.dist-info/RECORD
spotify_downloader-0.4.2.dist-info/WHEEL
spotify_downloader-0.4.2.dist-info/entry_points.txt
spotify_downloader-0.4.2.dist-info/metadata.json
spotify_downloader-0.4.2.dist-info/top_level.txt
