Metadata-Version: 2.0
Name: spotify-downloader
Version: 0.4.2
Summary: A CLI tool to download albums on Spotify via youtube-dl.
Home-page: https://github.com/AnthonyBloomer
Author: Anthony Bloomer
Author-email: ant0@protonmail.ch
License: UNKNOWN
Keywords: spotify,youtube,spotify-downloader,music,youtube-dl
Platform: UNKNOWN
Classifier: Development Status :: 3 - Alpha
Classifier: Environment :: Console
Classifier: Intended Audience :: Developers
Classifier: Intended Audience :: End Users/Desktop
Classifier: Operating System :: OS Independent
Classifier: License :: OSI Approved :: MIT License
Classifier: Programming Language :: Python :: 2.7
Requires-Dist: eyed3
Requires-Dist: requests
Requires-Dist: spotipy
